bk7231tools/__init__.py
bk7231tools/__main__.py
bk7231tools/analysis/__init__.py
bk7231tools/analysis/crc16.py
bk7231tools/analysis/flash.py
bk7231tools/analysis/kvstorage.py
bk7231tools/analysis/rbl.py
bk7231tools/analysis/storage.py
bk7231tools/analysis/utils.py
bk7231tools/crypto/__init__.py
bk7231tools/crypto/code.py
bk7231tools/crypto/util.py
bk7231tools/serial/__init__.py
bk7231tools/serial/base/__init__.py
bk7231tools/serial/base/data.py
bk7231tools/serial/base/enums.py
bk7231tools/serial/base/interface.py
bk7231tools/serial/base/packets.py
bk7231tools/serial/cmd_hl_flash.py
bk7231tools/serial/cmd_ll_chip.py
bk7231tools/serial/cmd_ll_flash.py
bk7231tools/serial/legacy.py
bk7231tools/serial/linking.py
bk7231tools/serial/main.py
bk7231tools/serial/protocol.py
bk7231tools-2.1.0.dist-info/LICENSE
bk7231tools-2.1.0.dist-info/METADATA
bk7231tools-2.1.0.dist-info/WHEEL
bk7231tools-2.1.0.dist-info/entry_points.txt
bk7231tools-2.1.0.dist-info/RECORD
