Metadata-Version: 2.1
Name: bk7231tools
Version: 2.1.0
Summary: Tools to interact with and analyze artifacts for BK7231 MCUs
License: MIT
Author: Khaled Nassar
Author-email: kmhnassar@gmail.com
Requires-Python: >=3.7,<4.0
Classifier: License :: OSI Approved :: MIT License
Classifier: Programming Language :: Python :: 3
Classifier: Programming Language :: Python :: 3.7
Classifier: Programming Language :: Python :: 3.8
Classifier: Programming Language :: Python :: 3.9
Classifier: Programming Language :: Python :: 3.10
Classifier: Programming Language :: Python :: 3.11
Classifier: Programming Language :: Python :: 3.12
Classifier: Programming Language :: Python :: 3.13
Provides-Extra: cli
Requires-Dist: py-datastruct (>=1.0.0,<2.0.0)
Requires-Dist: pycryptodome (>=3.16.0,<4.0.0) ; extra == "cli"
Requires-Dist: pyserial (>=3.5,<4.0)
